azure/cognitiveservices/vision/computervision/__init__.py
azure/cognitiveservices/vision/computervision/_computer_vision_client.py
azure/cognitiveservices/vision/computervision/_configuration.py
azure/cognitiveservices/vision/computervision/py.typed
azure/cognitiveservices/vision/computervision/version.py
azure/cognitiveservices/vision/computervision/models/__init__.py
azure/cognitiveservices/vision/computervision/models/_computer_vision_client_enums.py
azure/cognitiveservices/vision/computervision/models/_models.py
azure/cognitiveservices/vision/computervision/models/_models_py3.py
azure/cognitiveservices/vision/computervision/operations/__init__.py
azure/cognitiveservices/vision/computervision/operations/_computer_vision_client_operations.py
azure_cognitiveservices_vision_computervision-0.9.1.dist-info/METADATA
azure_cognitiveservices_vision_computervision-0.9.1.dist-info/WHEEL
azure_cognitiveservices_vision_computervision-0.9.1.dist-info/top_level.txt
azure_cognitiveservices_vision_computervision-0.9.1.dist-info/RECORD
