Metadata-Version: 2.1
Name: azure-cognitiveservices-vision-computervision
Version: 0.9.1
Summary: Microsoft Azure Cognitive Services Computer Vision Client Library for Python
Home-page: https://github.com/Azure/azure-sdk-for-python
Author: Microsoft Corporation
Author-email: azpysdkhelp@microsoft.com
License: MIT License
Keywords: azure,azure sdk
Classifier: Development Status :: 7 - Inactive
Classifier: Programming Language :: Python
Classifier: Programming Language :: Python :: 2
Classifier: Programming Language :: Python :: 2.7
Classifier: Programming Language :: Python :: 3
Classifier: Programming Language :: Python :: 3.5
Classifier: Programming Language :: Python :: 3.6
Classifier: Programming Language :: Python :: 3.7
Classifier: Programming Language :: Python :: 3.8
Classifier: License :: OSI Approved :: MIT License
Requires-Dist: msrest>=0.6.21
Requires-Dist: azure-common~=1.1
Requires-Dist: azure-cognitiveservices-vision-nspkg; python_version < "3.0"
